{
  "dataset": "reddit2",
  "model": "gat",
  "device": "GPU",
  "optimal_k": 20,
  "optimal_total_time_ms": 5130.700776207471,
  "optimal_avg_time_ms": 256.5350388103735,
  "optimal_throughput_per_sec": 0.19490514914400903,
  "subgraphs": [
    {
      "id": 0,
      "nodes": 34118,
      "edges": 1410890,
      "time_ms": 385.8349080880682
    },
    {
      "id": 1,
      "nodes": 98559,
      "edges": 510718,
      "time_ms": 171.65196459667854
    },
    {
      "id": 2,
      "nodes": 35320,
      "edges": 897362,
      "time_ms": 241.58658740748794
    },
    {
      "id": 3,
      "nodes": 107205,
      "edges": 305652,
      "time_ms": 102.19141252494131
    },
    {
      "id": 4,
      "nodes": 48650,
      "edges": 1054060,
      "time_ms": 309.16158929466
    },
    {
      "id": 5,
      "nodes": 40646,
      "edges": 613520,
      "time_ms": 189.322067261039
    },
    {
      "id": 6,
      "nodes": 20003,
      "edges": 717674,
      "time_ms": 193.05343072572836
    },
    {
      "id": 7,
      "nodes": 92714,
      "edges": 468730,
      "time_ms": 157.04488820342078
    },
    {
      "id": 8,
      "nodes": 40258,
      "edges": 529560,
      "time_ms": 163.68370037933667
    },
    {
      "id": 9,
      "nodes": 50672,
      "edges": 855298,
      "time_ms": 260.08634476108284
    },
    {
      "id": 10,
      "nodes": 34888,
      "edges": 569336,
      "time_ms": 168.01808388571033
    },
    {
      "id": 11,
      "nodes": 66184,
      "edges": 822456,
      "time_ms": 264.7270425704621
    },
    {
      "id": 12,
      "nodes": 67471,
      "edges": 940480,
      "time_ms": 302.55225316499684
    },
    {
      "id": 13,
      "nodes": 71235,
      "edges": 707860,
      "time_ms": 231.36821378334736
    },
    {
      "id": 14,
      "nodes": 51496,
      "edges": 873846,
      "time_ms": 264.7105517288107
    },
    {
      "id": 15,
      "nodes": 67006,
      "edges": 966454,
      "time_ms": 310.1913180903575
    },
    {
      "id": 16,
      "nodes": 47995,
      "edges": 940876,
      "time_ms": 281.48650607218985
    },
    {
      "id": 17,
      "nodes": 80826,
      "edges": 1132460,
      "time_ms": 374.24880053126526
    },
    {
      "id": 18,
      "nodes": 104487,
      "edges": 1281168,
      "time_ms": 429.3984578804381
    },
    {
      "id": 19,
      "nodes": 36428,
      "edges": 1210770,
      "time_ms": 330.3826552574493
    }
  ]
}